{
  "submissions": [
    {
      "id": "submission-85b93e18-d48a-4792-9f72-81b80bbe6e7f",
      "producerName": "test",
      "contactInfo": "test",
      "wineName": "test",
      "wineType": "red",
      "grapeVariety": "test",
      "year": 2026,
      "price": 100,
      "region": "Codru",
      "sweetness": "dry",
      "body": "medium",
      "alcoholPercent": 12,
      "aromaNotes": [
        "test"
      ],
      "suggestedPairingTags": [
        "test"
      ],
      "productionMethod": "test",
      "status": "approved",
      "reviewerComment": "",
      "createdAt": 1778021532336,
      "updatedAt": 1778021551577
    }
  ],
  "approvedWines": [
    {
      "id": "wine-695f561c-1dd3-43fc-acd8-1760e8c4e7c0",
      "wineryId": null,
      "name": "test",
      "type": "red",
      "grapeVariety": "test (test)",
      "year": 2026,
      "price": 100,
      "region": "Codru",
      "body": "medium",
      "sweetness": "dry",
      "aromaNotes": [
        "test"
      ],
      "servingTemp": "10-16 C",
      "alcoholPercent": 12,
      "pairingTags": [
        "test"
      ],
      "liked": false,
      "sourceType": "producer-approved",
      "createdAt": 1778021551577,
      "updatedAt": 1778021551577
    }
  ]
}